vecs2pauli/__init__.py
vecs2pauli/_vecs2pauli.cp310-win_amd64.pyd
vecs2pauli/converter.py
vecs2pauli/stabilizers2vectors.py
vecs2pauli/vecs2pauli.py
vecs2pauli/include/vecs2pauli.hpp
vecs2pauli/lib/vecs2pauli.lib
vecs2pauli/lib/cmake/vecs2pauli/vecs2pauli-config-release.cmake
vecs2pauli/lib/cmake/vecs2pauli/vecs2pauli-config.cmake
vecs2pauli-0.0.1.dist-info/LICENSE.md
vecs2pauli-0.0.1.dist-info/METADATA
vecs2pauli-0.0.1.dist-info/WHEEL
vecs2pauli-0.0.1.dist-info/top_level.txt
vecs2pauli-0.0.1.dist-info/RECORD
