Metadata-Version: 2.1
Name: vecs2pauli
Version: 0.0.1
Maintainer: Tim Coopmans
License: MIT
Classifier: Programming Language :: Python :: 3
Classifier: Operating System :: OS Independent
Classifier: License :: OSI Approved :: MIT License
Requires-Python: >=3.8
License-File: LICENSE.md
Requires-Dist: numpy ==1.26.2
Requires-Dist: pytest ==7.4.3
